pyclugen/__init__.py
pyclugen/core.py
pyclugen/helper.py
pyclugen/main.py
pyclugen/module.py
pyclugen/py.typed
pyclugen/shared.py
pyclugen-1.1.4.dist-info/licenses/LICENSE.txt
pyclugen-1.1.4.dist-info/METADATA
pyclugen-1.1.4.dist-info/WHEEL
pyclugen-1.1.4.dist-info/top_level.txt
pyclugen-1.1.4.dist-info/RECORD
