Metadata-Version: 2.4
Name: pyclugen
Version: 1.1.4
Summary: Multidimensional cluster generation in Python
Author-email: Nuno Fachada <faken@fakenmc.com>
License: MIT
Project-URL: Bug Reports, https://github.com/clugen/pyclugen/issues
Project-URL: Documentation, https://clugen.github.io/pyclugen/
Project-URL: Source, https://github.com/clugen/pyclugen/
Keywords: multidimensional data,synthetic clusters,synthetic data generation,synthetic data generator,multidimensional clusters,clustering
Classifier: Development Status :: 5 - Production/Stable
Classifier: Programming Language :: Python :: 3
Classifier: Intended Audience :: Science/Research
Classifier: License :: OSI Approved :: MIT License
Classifier: Operating System :: OS Independent
Classifier: Topic :: Scientific/Engineering
Requires-Python: >=3.8
License-File: LICENSE.txt
Requires-Dist: numpy>=1.20
Provides-Extra: dev
Requires-Dist: black; extra == "dev"
Requires-Dist: flake8>=6.0.0; extra == "dev"
Requires-Dist: flake8-black; extra == "dev"
Requires-Dist: flake8-builtins; extra == "dev"
Requires-Dist: flake8-bugbear; extra == "dev"
Requires-Dist: flake8-comprehensions; extra == "dev"
Requires-Dist: flake8-docstrings; extra == "dev"
Requires-Dist: flake8-isort; extra == "dev"
Requires-Dist: Flake8-pyproject; extra == "dev"
Requires-Dist: flake8-pytest-style; extra == "dev"
Requires-Dist: flake8-simplify; extra == "dev"
Requires-Dist: isort; extra == "dev"
Requires-Dist: matplotlib; extra == "dev"
Requires-Dist: mypy; extra == "dev"
Requires-Dist: mkdocs-gallery; extra == "dev"
Requires-Dist: mkdocs-material; extra == "dev"
Requires-Dist: mkdocstrings-python; extra == "dev"
Requires-Dist: pandas; extra == "dev"
Requires-Dist: pep8-naming; extra == "dev"
Requires-Dist: pre-commit; extra == "dev"
Requires-Dist: pytest>=6.0; extra == "dev"
Requires-Dist: coverage; extra == "dev"
Requires-Dist: pytest-cov>=3.0.0; extra == "dev"
Requires-Dist: pytest-mypy; extra == "dev"
Requires-Dist: scikit-learn; extra == "dev"
Requires-Dist: seaborn; extra == "dev"
Dynamic: license-file
